screenplay/__init__.py
screenplay/pattern.py
screenplay-0.1.5.dist-info/LICENSE
screenplay-0.1.5.dist-info/METADATA
screenplay-0.1.5.dist-info/WHEEL
screenplay-0.1.5.dist-info/top_level.txt
screenplay-0.1.5.dist-info/RECORD
