Metadata-Version: 2.1
Name: screenplay
Version: 0.1.5
Summary: The Python Screenplay Pattern
Home-page: https://github.com/AutomationPanda/screenplay
Author: Pandy Knight
Author-email: 
License: UNKNOWN
Project-URL: Bug Tracker, https://github.com/AutomationPanda/screenplay/issues
Platform: UNKNOWN
Classifier: Intended Audience :: Developers
Classifier: Programming Language :: Python :: 3
Classifier: License :: OSI Approved :: MIT License
Classifier: Operating System :: OS Independent
Classifier: Topic :: Software Development :: Testing
Requires-Python: >=3.7
License-File: LICENSE
